{"type": "FeatureCollection", "features": [{"type": "Feature", "id": "address.349612", "geometry": {"type": "Point", "coordinates": [12.46442653, 55.63197121]}, "geometry_name": "geometri", "properties": {"ogc_fid": 349612, "inspireid": "0a3f507c-e63f-32b8-e044-0003ba298018", "alternativeidentifier": null, "position_default": "1", "status": "current", "locator_designator_1_designator": "14", "locator_designator_1_type": "entrancedooridentifier", "locator_name_name": null, "locator_name_type": null, "locator_level": "accesslevel", "locator_withinscopeof_addressareaname": null, "locator_withinscopeof_adminunitname": "https://api.dataforsyningen.dk/ogcapi/features/ad_inspire/collections/adminunitname/items/389113?f=json", "locator_withinscopeof_postaldescriptor": "https://api.dataforsyningen.dk/ogcapi/features/ad_inspire/collections/postaldescriptor/items/d527c78a-62f2-4705-b9b2-89800dc299ae?f=json", "locator_withinscopeof_thoroughfarename": "https://api.dataforsyningen.dk/ogcapi/features/ad_inspire/collections/thoroughfarename/items/b4174c13-97b6-45ae-b8bf-302cd37bcd7a?f=json", "locator_designator_2_designator": null, "locator_designator_2_type": "flooridentifier", "locator_designator_3_designator": null, "locator_designator_3_type": "unitidentifier", "validfrom": "2018-07-04T16:00:00Z", "validto": null, "beginlifespanversion": "2018-07-04T16:00:00Z", "endlifespanversion": null, "parentaddress": null, "component_addressareaname_1": null, "component_addressareaname_2": null, "component_addressareaname_3": null, "component_adminunitname_1": null, "component_adminunitname_2": "https://api.dataforsyningen.dk/ogcapi/features/ad_inspire/collections/adminunitname/items/389099?f=json", "component_adminunitname_3": "https://api.dataforsyningen.dk/ogcapi/features/ad_inspire/collections/adminunitname/items/389113?f=json", "component_adminunitname_4": null, "component_adminunitname_5": null, "component_adminunitname_6": null, "component_postaldescriptor": "https://api.dataforsyningen.dk/ogcapi/features/ad_inspire/collections/postaldescriptor/items/d527c78a-62f2-4705-b9b2-89800dc299ae?f=json", "component_thoroughfarename": "https://api.dataforsyningen.dk/ogcapi/features/ad_inspire/collections/thoroughfarename/items/b4174c13-97b6-45ae-b8bf-302cd37bcd7a?f=json", "parcel": "https://api.dataforsyningen.dk/ogcapi/features/cp_inspire/collections/cadastralparcel/items/267593?f=json", "building": "https://api.dataforsyningen.dk/ogcapi/features/building_inspire/collections/building/items/1110604887?f=json", "position_specification": "addressarea", "position_method": "byotherparty"}}], "totalFeatures": 1, "numberMatched": 1, "numberReturned": 1, "timeStamp": "2025-12-19T10:57:43.937Z", "crs": {"type": "name", "properties": {"name": "urn:ogc:def:crs:EPSG::4326"}}}